odoo/addons/account_invoice_ubl_email_attachment/README.rst
odoo/addons/account_invoice_ubl_email_attachment/__init__.py
odoo/addons/account_invoice_ubl_email_attachment/__manifest__.py
odoo/addons/account_invoice_ubl_email_attachment/i18n/account_invoice_ubl_email_attachment.pot
odoo/addons/account_invoice_ubl_email_attachment/i18n/de.po
odoo/addons/account_invoice_ubl_email_attachment/i18n/hr.po
odoo/addons/account_invoice_ubl_email_attachment/i18n/nl.po
odoo/addons/account_invoice_ubl_email_attachment/models/__init__.py
odoo/addons/account_invoice_ubl_email_attachment/models/account_move.py
odoo/addons/account_invoice_ubl_email_attachment/models/mail_template.py
odoo/addons/account_invoice_ubl_email_attachment/models/res_company.py
odoo/addons/account_invoice_ubl_email_attachment/models/res_config_settings.py
odoo/addons/account_invoice_ubl_email_attachment/readme/CONFIGURE.rst
odoo/addons/account_invoice_ubl_email_attachment/readme/CONTRIBUTORS.rst
odoo/addons/account_invoice_ubl_email_attachment/readme/DESCRIPTION.rst
odoo/addons/account_invoice_ubl_email_attachment/readme/USAGE.rst
odoo/addons/account_invoice_ubl_email_attachment/static/description/icon.png
odoo/addons/account_invoice_ubl_email_attachment/static/description/index.html
odoo/addons/account_invoice_ubl_email_attachment/tests/__init__.py
odoo/addons/account_invoice_ubl_email_attachment/tests/test_ubl_email_attachment.py
odoo/addons/account_invoice_ubl_email_attachment/views/res_config_settings.xml
odoo13_addon_account_invoice_ubl_email_attachment-13.0.1.1.1.dist-info/METADATA
odoo13_addon_account_invoice_ubl_email_attachment-13.0.1.1.1.dist-info/WHEEL
odoo13_addon_account_invoice_ubl_email_attachment-13.0.1.1.1.dist-info/top_level.txt
odoo13_addon_account_invoice_ubl_email_attachment-13.0.1.1.1.dist-info/RECORD
