Metadata-Version: 2.1
Name: odoo13-addon-account-invoice-ubl-email-attachment
Version: 13.0.1.1.1
Summary: Automatically adds the UBL file to the email.
Home-page: https://github.com/OCA/edi
Author: Onestein, Odoo Community Association (OCA)
Author-email: support@odoo-community.org
License: AGPL-3
Platform: UNKNOWN
Classifier: Programming Language :: Python
Classifier: Framework :: Odoo
Classifier: Framework :: Odoo :: 13.0
Classifier: License :: OSI Approved :: GNU Affero General Public License v3
Requires-Python: >=3.5
Requires-Dist: odoo13-addon-account-invoice-ubl
Requires-Dist: odoo (<13.1dev,>=13.0a)
